loggingutil/__init__.py
loggingutil/adapter.py
loggingutil/cli.py
loggingutil/config.py
loggingutil/filters.py
loggingutil/handlers.py
loggingutil-2.0.1.dist-info/licenses/LICENSE
loggingutil-2.0.1.dist-info/METADATA
loggingutil-2.0.1.dist-info/WHEEL
loggingutil-2.0.1.dist-info/entry_points.txt
loggingutil-2.0.1.dist-info/top_level.txt
loggingutil-2.0.1.dist-info/RECORD
