Metadata-Version: 2.4
Name: loggingutil
Version: 2.0.1
Summary: A powerful logging utility that surpasses the standard library
Home-page: https://github.com/mochathehuman/loggingutil
Author: Mocha
Author-email: ohplot@gmail.com
Project-URL: Bug Tracker, https://github.com/mochathehuman/loggingutil/issues
Project-URL: Source, https://github.com/mochathehuman/loggingutil
Project-URL: Documentation, https://mochathehuman.github.io/loggingutil/
Keywords: logging,logs,structured-logging,async-logging,log-rotation,monitoring,observability,cloudwatch,elasticsearch,prometheus
Classifier: Development Status :: 5 - Production/Stable
Classifier: Intended Audience :: Developers
Classifier: License :: OSI Approved :: MIT License
Classifier: Operating System :: OS Independent
Classifier: Programming Language :: Python :: 3
Classifier: Programming Language :: Python :: 3.8
Classifier: Programming Language :: Python :: 3.9
Classifier: Programming Language :: Python :: 3.10
Classifier: Programming Language :: Python :: 3.11
Classifier: Topic :: System :: Logging
Classifier: Framework :: AsyncIO
Classifier: Intended Audience :: System Administrators
Classifier: Intended Audience :: Information Technology
Classifier: Topic :: System :: Monitoring
Requires-Python: >=3.8
License-File: LICENSE
Requires-Dist: aiohttp>=3.8.0
Requires-Dist: pyyaml>=5.1
Requires-Dist: click>=8.0.0
Provides-Extra: aws
Requires-Dist: boto3>=1.26.0; extra == "aws"
Provides-Extra: elastic
Requires-Dist: elasticsearch>=7.0.0; extra == "elastic"
Provides-Extra: metrics
Requires-Dist: prometheus_client>=0.16.0; extra == "metrics"
Provides-Extra: structlog
Requires-Dist: structlog>=22.1.0; extra == "structlog"
Provides-Extra: all
Requires-Dist: boto3>=1.26.0; extra == "all"
Requires-Dist: elasticsearch>=7.0.0; extra == "all"
Requires-Dist: prometheus_client>=0.16.0; extra == "all"
Requires-Dist: structlog>=22.1.0; extra == "all"
Requires-Dist: rich>=12.0.0; extra == "all"
Requires-Dist: tabulate>=0.8.0; extra == "all"
Dynamic: author
Dynamic: author-email
Dynamic: classifier
Dynamic: description
Dynamic: description-content-type
Dynamic: home-page
Dynamic: keywords
Dynamic: license-file
Dynamic: project-url
Dynamic: provides-extra
Dynamic: requires-dist
Dynamic: requires-python
Dynamic: summary
